decimctl/__init__.py
decimctl/protocol.py
decimctl-0.4.data/scripts/decimctl
decimctl-0.4.dist-info/LICENSE
decimctl-0.4.dist-info/METADATA
decimctl-0.4.dist-info/WHEEL
decimctl-0.4.dist-info/top_level.txt
decimctl-0.4.dist-info/zip-safe
decimctl-0.4.dist-info/RECORD
