Metadata-Version: 2.1
Name: decimctl
Version: 0.4
Summary: Library for controlling products from Decimator Design
Home-page: https://github.com/quentinmit/decimctl
Author: Quentin Smith
Author-email: quentin@mit.edu
License: Apache 2.0
Platform: UNKNOWN
License-File: LICENSE
Requires-Dist: pylibftdi
